openai_tools_gpt/__init__.py
openai_tools_gpt/main.py
openai_tools_gpt-0.1.6.dist-info/METADATA
openai_tools_gpt-0.1.6.dist-info/WHEEL
openai_tools_gpt-0.1.6.dist-info/top_level.txt
openai_tools_gpt-0.1.6.dist-info/RECORD
