Metadata-Version: 2.1
Name: openai-tools-gpt
Version: 0.1.6
Requires-Dist: openai >=1.12.0
Requires-Dist: retry >=0.9.2
Requires-Dist: python-dotenv >=1.0.1
